LICENSE
README.md
setup.py
TonTools/__init__.py
TonTools.egg-info/PKG-INFO
TonTools.egg-info/SOURCES.txt
TonTools.egg-info/dependency_links.txt
TonTools.egg-info/requires.txt
TonTools.egg-info/top_level.txt
TonTools/Contracts/Contract.py
TonTools/Contracts/Jetton.py
TonTools/Contracts/NFT.py
TonTools/Contracts/Wallet.py
TonTools/Contracts/utils.py
TonTools/Providers/DtonClient.py
TonTools/Providers/LsClient.py
TonTools/Providers/TonApiClient.py
TonTools/Providers/TonCenterClient.py
TonTools/Providers/_orbs_ton_access.py
TonTools/Providers/utils.py