Metadata-Version: 2.1
Name: TonTools
Version: 2.1.2
Summary: Explore TON Blockchain with python
Home-page: 
Author: yungwine
Author-email: cyrbatoff@gmail.com
License: MIT License
License-File: LICENSE
